qacaller/Test.py
qacaller/__init__.py
qacaller/listener.py
qacaller-0.1.2.dist-info/METADATA
qacaller-0.1.2.dist-info/WHEEL
qacaller-0.1.2.dist-info/entry_points.txt
qacaller-0.1.2.dist-info/top_level.txt
qacaller-0.1.2.dist-info/RECORD
